nflx_jupyterlab_slackfeedback/__init__.py
nflx_jupyterlab_slackfeedback/_version.py
nflx_jupyterlab_slackfeedback/labextension/build_log.json
nflx_jupyterlab_slackfeedback/labextension/package.json
nflx_jupyterlab_slackfeedback/labextension/static/lib_index_js.64245daedae06a27ba55.js
nflx_jupyterlab_slackfeedback/labextension/static/lib_index_js.64245daedae06a27ba55.js.map
nflx_jupyterlab_slackfeedback/labextension/static/remoteEntry.434058dd118b06131529.js
nflx_jupyterlab_slackfeedback/labextension/static/remoteEntry.434058dd118b06131529.js.map
nflx_jupyterlab_slackfeedback/labextension/static/style.js
nflx_jupyterlab_slackfeedback/labextension/static/style_index_js.4daa089a3703a0ca6898.js
nflx_jupyterlab_slackfeedback/labextension/static/style_index_js.4daa089a3703a0ca6898.js.map
nflx_jupyterlab_slackfeedback/labextension/static/vendors-node_modules_css-loader_dist_runtime_api_js-node_modules_css-loader_dist_runtime_cssW-72eba1.30208a5ed8674c09f80e.js
nflx_jupyterlab_slackfeedback/labextension/static/vendors-node_modules_css-loader_dist_runtime_api_js-node_modules_css-loader_dist_runtime_cssW-72eba1.30208a5ed8674c09f80e.js.map
nflx_jupyterlab_slackfeedback/labextension/static/vendors-node_modules_material-ui_core_esm_index_js.4d29e2d456b28f99dbbc.js
nflx_jupyterlab_slackfeedback/labextension/static/vendors-node_modules_material-ui_core_esm_index_js.4d29e2d456b28f99dbbc.js.map
nflx_jupyterlab_slackfeedback/labextension/static/vendors-node_modules_react-slack-feedback_dist_index_esm_js.3cdf506ea3e5fdae87e3.js
nflx_jupyterlab_slackfeedback/labextension/static/vendors-node_modules_react-slack-feedback_dist_index_esm_js.3cdf506ea3e5fdae87e3.js.map
nflx_jupyterlab_slackfeedback/labextension/static/vendors-node_modules_typestyle_lib_es2015_index_js.ed968272879f5826d4f0.js
nflx_jupyterlab_slackfeedback/labextension/static/vendors-node_modules_typestyle_lib_es2015_index_js.ed968272879f5826d4f0.js.map
nflx_jupyterlab_slackfeedback-0.1.0.dist-info/LICENSE
nflx_jupyterlab_slackfeedback-0.1.0.dist-info/METADATA
nflx_jupyterlab_slackfeedback-0.1.0.dist-info/WHEEL
nflx_jupyterlab_slackfeedback-0.1.0.dist-info/top_level.txt
nflx_jupyterlab_slackfeedback-0.1.0.dist-info/RECORD
