Metadata-Version: 2.1
Name: nflx-jupyterlab-slackfeedback
Version: 0.1.0
Summary: A jupyter lab extension to allow users send feedback to the notebooks team using slack.
Home-page: https://stash.corp.netflix.com/projects/nflx_jupyterlab_slackfeedback/repos/nflx-jupyterlab-slackfeedback
Author: E
Author-email: eaninye@netflix.com
License: BSD-3-Clause
Keywords: Jupyter,JupyterLab,JupyterLab3
Platform: Linux
Platform: Mac OS X
Platform: Windows
Classifier: License :: OSI Approved :: BSD License
Classifier: Programming Language :: Python
Classifier: Programming Language :: Python :: 3
Classifier: Programming Language :: Python :: 3.7
Classifier: Programming Language :: Python :: 3.8
Classifier: Programming Language :: Python :: 3.9
Classifier: Programming Language :: Python :: 3.10
Classifier: Framework :: Jupyter
Classifier: Framework :: Jupyter :: JupyterLab
Classifier: Framework :: Jupyter :: JupyterLab :: 3
Classifier: Framework :: Jupyter :: JupyterLab :: Extensions
Classifier: Framework :: Jupyter :: JupyterLab :: Extensions :: Prebuilt
Requires-Python: >=3.7
License-File: LICENSE
Requires-Dist: nflx-jl-analytics
